{
  "mappings":[
    {
      "hardwareName":"ExampleHardware1",
      "makeSpan":272,
      "width":108,
      "energy":38116,
      "taskMapping":[
        {
          "task":"inputting",
          "processingElement":"procA",
          "implementation":"cpu_standard",
          "parameters":[],
          "start":0,
          "duration":11,
          "end":11
        },
        {
          "task":"decoding",
          "processingElement":"GPGPU1",
          "implementation":"gpgpu_standard",
          "parameters":[],
          "start":64,
          "duration":10,
          "end":74
        },
        {
          "task":"Transforming",
          "processingElement":"procA",
          "implementation":"cpu_standard",
          "parameters":[],
          "start":96,
          "duration":12,
          "end":108
        },
        {
          "task":"Transforming2",
          "processingElement":"procA",
          "implementation":"cpu_standard",
          "parameters":[],
          "start":83,
          "duration":12,
          "end":95
        },
        {
          "task":"watermarking",
          "processingElement":"GPGPU1",
          "implementation":"gpgpu_standard",
          "parameters":[],
          "start":113,
          "duration":10,
          "end":123
        },
        {
          "task":"encoding",
          "processingElement":"procB",
          "implementation":"cpu_param",
          "parameters":[
            {
              "name":"toto",
              "value":2
            }
          ],
          "start":166,
          "duration":106,
          "end":272
        }
      ],
      "transmissionMapping":[
        {
          "transmission":"inputToDecode",
          "bus":"busAtoGPGPU",
          "start":12,
          "duration":51,
          "end":63
        },
        {
          "transmission":"decodeToTransform",
          "bus":"busAtoGPGPU",
          "start":75,
          "duration":3,
          "end":78
        },
        {
          "transmission":"transformToWatermark",
          "bus":"busAtoGPGPU",
          "start":109,
          "duration":3,
          "end":112
        },
        {
          "transmission":"decodeToTransform2",
          "bus":"globalBus",
          "start":75,
          "duration":7,
          "end":82
        },
        {
          "transmission":"transform2ToWatermark",
          "bus":"busAtoGPGPU",
          "start":96,
          "duration":3,
          "end":99
        },
        {
          "transmission":"watermarkToEncode",
          "bus":"busBToGPGPU",
          "start":124,
          "duration":41,
          "end":165
        },
        {
          "transmission":"side_comm",
          "bus":"globalBus",
          "start":12,
          "duration":16,
          "end":28
        }
      ]
    },
    {
      "hardwareName":"ExampleHardware1",
      "makeSpan":275,
      "width":194,
      "energy":37930,
      "taskMapping":[
        {
          "task":"inputting",
          "processingElement":"procA",
          "implementation":"cpu_standard",
          "parameters":[],
          "start":0,
          "duration":11,
          "end":11
        },
        {
          "task":"decoding",
          "processingElement":"GPGPU1",
          "implementation":"gpgpu_standard",
          "parameters":[],
          "start":64,
          "duration":10,
          "end":74
        },
        {
          "task":"Transforming",
          "processingElement":"procA",
          "implementation":"cpu_standard",
          "parameters":[],
          "start":79,
          "duration":12,
          "end":91
        },
        {
          "task":"Transforming2",
          "processingElement":"procB",
          "implementation":"cpu_standard",
          "parameters":[],
          "start":81,
          "duration":28,
          "end":109
        },
        {
          "task":"watermarking",
          "processingElement":"GPGPU1",
          "implementation":"gpgpu_standard",
          "parameters":[],
          "start":116,
          "duration":10,
          "end":126
        },
        {
          "task":"encoding",
          "processingElement":"procB",
          "implementation":"cpu_param",
          "parameters":[
            {
              "name":"toto",
              "value":2
            }
          ],
          "start":169,
          "duration":106,
          "end":275
        }
      ],
      "transmissionMapping":[
        {
          "transmission":"inputToDecode",
          "bus":"busAtoGPGPU",
          "start":12,
          "duration":51,
          "end":63
        },
        {
          "transmission":"decodeToTransform",
          "bus":"busAtoGPGPU",
          "start":75,
          "duration":3,
          "end":78
        },
        {
          "transmission":"transformToWatermark",
          "bus":"busAtoGPGPU",
          "start":92,
          "duration":3,
          "end":95
        },
        {
          "transmission":"decodeToTransform2",
          "bus":"busBToGPGPU",
          "start":75,
          "duration":5,
          "end":80
        },
        {
          "transmission":"transform2ToWatermark",
          "bus":"busBToGPGPU",
          "start":110,
          "duration":5,
          "end":115
        },
        {
          "transmission":"watermarkToEncode",
          "bus":"busBToGPGPU",
          "start":127,
          "duration":41,
          "end":168
        },
        {
          "transmission":"side_comm",
          "bus":"globalBus",
          "start":12,
          "duration":16,
          "end":28
        }
      ]
    }
  ]
}