{
  "timeUnit":"ms",
  "dataUnit":"bit",
  "info":"",
  "mappings":[
    {
      "hardwareName":"ExampleHardware1",
      "makeSpan":114,
      "energy":34998,
      "sharedFunctions":[],
      "taskMapping":[
        {
          "task":"input",
          "processingElement":"procA",
          "implementation":"cpu_standard",
          "parameters":[],
          "start":0,
          "duration":11,
          "end":11
        },
        {
          "task":"transform",
          "processingElement":"procA",
          "implementation":"cpu_standard",
          "parameters":[],
          "start":11,
          "duration":12,
          "end":23
        },
        {
          "task":"output",
          "processingElement":"procA",
          "implementation":"cpu_param",
          "parameters":[
            {
              "name":"toto",
              "value":2
            }
          ],
          "start":23,
          "duration":91,
          "end":114
        }
      ],
      "transmissionMapping":[]
    },
    {
      "hardwareName":"ExampleHardware1",
      "makeSpan":254,
      "energy":32678,
      "sharedFunctions":[],
      "taskMapping":[
        {
          "task":"input",
          "processingElement":"FPGA1",
          "implementation":"fpga_standard",
          "parameters":[],
          "start":0,
          "duration":0,
          "end":0
        },
        {
          "task":"transform",
          "processingElement":"procA",
          "implementation":"cpu_standard",
          "parameters":[],
          "start":151,
          "duration":12,
          "end":163
        },
        {
          "task":"output",
          "processingElement":"procA",
          "implementation":"cpu_param",
          "parameters":[
            {
              "name":"toto",
              "value":2
            }
          ],
          "start":163,
          "duration":91,
          "end":254
        }
      ],
      "transmissionMapping":[
        {
          "transmission":"inputToTransform",
          "bus":"globalBus",
          "start":0,
          "duration":151,
          "end":151
        },
        {
          "transmission":"inputToOutput",
          "bus":"globalBus",
          "start":151,
          "duration":7,
          "end":158
        }
      ]
    }
  ]
}